README.rst
setup.py
crypko/__init__.py
crypko/abi.json
crypko/api.py
crypko/blockchain.py
crypko/errors.py
crypko/objects.py
crypko.py.egg-info/PKG-INFO
crypko.py.egg-info/SOURCES.txt
crypko.py.egg-info/dependency_links.txt
crypko.py.egg-info/requires.txt
crypko.py.egg-info/top_level.txt
crypko/examples/auto_fuse.py
crypko/examples/download_all.py