Metadata-Version: 1.0
Name: crypko.py
Version: 0.0.4
Summary: A basic wrapper around the Crypko platform.
Home-page: https://gitlab.com/Bottersnike/crypko.py
Author: Bottersnike
Author-email: bottersnik237@gmail.com
License: MIT
Project-URL: Bug Tracker, https://gitlab.com/Bottersnike/crypko.py/issues
Project-URL: Source Code, https://gitlab.com/Bottersnike/crypko.py
Platform: UNKNOWN
